{"devicePlatform":"","logFolder":"C:\\Users\\KHilmi\\Katalon Studio\\AMS_TestProject\\Reports\\TestSuite_01_LoginFunction\\20180712_111701","runData":{"hostName":"KHilmi - MYPEN02ITSN044.kerrylogistics.com","os":"Windows 10 64bit","katalonVersion":"5.4.2.1","browser":"Chrome 67.0.3396.99","hostAddress":"172.27.8.136","sessionId":"93de73ecadfcfec34167f64aa702e2b2","seleniumVersion":"3.7.1","proxyInformation":"ProxyInformation{proxyOption\u003dNO_PROXY, proxyServerType\u003dHTTP, password\u003d, proxyServerAddress\u003d, proxyServerPort\u003d0}","platform":"Windows 10"},"type":"TEST_SUITE","name":"TestSuite_01_LoginFunction","id":"Test Suites/TestSuite_01_LoginFunction","source":"","message":"Test Cases/TC05_LoginWithValidUsernamePasswordButFail FAILED because (of) Unable to verify object is present (Root cause: java.lang.IllegalArgumentException: Object is null)","description":"","startTime":1531365424515,"endTime":1531365471186,"childRecords":[{"isOptional":false,"type":"TEST_CASE","name":"Test Cases/TC01_LoginWithValidUsernamePassword","id":"Test Cases/TC01_LoginWithValidUsernamePassword","source":"C:\\\\Users\\\\KHilmi\\\\Katalon Studio\\\\AMS_TestProject\\\\Test Cases\\\\TC01_LoginWithValidUsernamePassword.tc","message":"Test Cases/TC01_LoginWithValidUsernamePassword","description":"","startTime":1531365425003,"endTime":1531365439359,"childRecords":[{"testStatus":{"stackTrace":"","statusValue":"INFO"},"type":"MESSAGE","name":"","message":"Evaluating variables for test case","startTime":1531365425041,"endTime":0,"childRecords":[],"interuppted":false},{"index":1,"isIgnoredIfFailed":false,"type":"TEST_STEP","name":"openBrowser","message":"Browser is opened with url: \u0027\u0027","description":"","startTime":1531365425689,"endTime":1531365430755,"childRecords":[{"testStatus":{"stackTrace":"","statusValue":"PASSED"},"type":"MESSAGE","name":"","message":"Browser is opened with url: \u0027\u0027","startTime":1531365430754,"endTime":0,"childRecords":[],"interuppted":false}],"interuppted":false},{"index":2,"isIgnoredIfFailed":false,"type":"TEST_STEP","name":"navigateToUrl","message":"Navigate to \u0027http://localhost:57065/account/login\u0027 successfully","description":"","startTime":1531365430755,"endTime":1531365432629,"childRecords":[{"testStatus":{"stackTrace":"","statusValue":"PASSED"},"type":"MESSAGE","name":"","message":"Navigate to \u0027http://localhost:57065/account/login\u0027 successfully","startTime":1531365432628,"endTime":0,"childRecords":[],"interuppted":false}],"interuppted":false},{"index":3,"isIgnoredIfFailed":false,"type":"TEST_STEP","name":"setText","message":"Text \u0027KHilmi\u0027 is set on object \u0027Object Repository/TC01_OR/Page_Login/input_UserName\u0027","description":"","startTime":1531365432629,"endTime":1531365433104,"childRecords":[{"testStatus":{"stackTrace":"","statusValue":"PASSED"},"type":"MESSAGE","name":"","message":"Text \u0027KHilmi\u0027 is set on object \u0027Object Repository/TC01_OR/Page_Login/input_UserName\u0027","startTime":1531365433104,"endTime":0,"childRecords":[],"interuppted":false}],"interuppted":false},{"index":4,"isIgnoredIfFailed":false,"type":"TEST_STEP","name":"setText","message":"Text \u0027P@ssw0rd\u0027 is set on object \u0027Object Repository/TC01_OR/Page_Login/input_Password\u0027","description":"","startTime":1531365433105,"endTime":1531365433474,"childRecords":[{"testStatus":{"stackTrace":"","statusValue":"PASSED"},"type":"MESSAGE","name":"","message":"Text \u0027P@ssw0rd\u0027 is set on object \u0027Object Repository/TC01_OR/Page_Login/input_Password\u0027","startTime":1531365433473,"endTime":0,"childRecords":[],"interuppted":false}],"interuppted":false},{"index":5,"isIgnoredIfFailed":false,"type":"TEST_STEP","name":"click","message":"Object: \u0027Object Repository/TC01_OR/Page_Login/input_btn btn-primary\u0027 is clicked on","description":"","startTime":1531365433474,"endTime":1531365437485,"childRecords":[{"testStatus":{"stackTrace":"","statusValue":"PASSED"},"type":"MESSAGE","name":"","message":"Object: \u0027Object Repository/TC01_OR/Page_Login/input_btn btn-primary\u0027 is clicked on","startTime":1531365437484,"endTime":0,"childRecords":[],"interuppted":false}],"interuppted":false},{"index":6,"isIgnoredIfFailed":false,"type":"TEST_STEP","name":"click","message":"Object: \u0027Object Repository/TC01_OR/Page_Asset Management System/h2_Dashboard\u0027 is clicked on","description":"","startTime":1531365437485,"endTime":1531365437791,"childRecords":[{"testStatus":{"stackTrace":"","statusValue":"PASSED"},"type":"MESSAGE","name":"","message":"Object: \u0027Object Repository/TC01_OR/Page_Asset Management System/h2_Dashboard\u0027 is clicked on","startTime":1531365437790,"endTime":0,"childRecords":[],"interuppted":false}],"interuppted":false},{"index":7,"isIgnoredIfFailed":false,"type":"TEST_STEP","name":"verifyElementPresent","message":"Object \u0027Object Repository/TC01_OR/Page_Asset Management System/h2_Dashboard\u0027 is present","description":"","startTime":1531365437791,"endTime":1531365437861,"childRecords":[{"testStatus":{"stackTrace":"","statusValue":"WARNING"},"type":"MESSAGE","name":"","message":"Timeout \u00270\u0027 is invalid. Using default page load timeout: \u00275\u0027","startTime":1531365437806,"endTime":0,"childRecords":[],"interuppted":false},{"testStatus":{"stackTrace":"","statusValue":"PASSED"},"type":"MESSAGE","name":"","message":"Object \u0027Object Repository/TC01_OR/Page_Asset Management System/h2_Dashboard\u0027 is present","startTime":1531365437861,"endTime":0,"childRecords":[],"interuppted":false}],"interuppted":false},{"index":8,"isIgnoredIfFailed":false,"type":"TEST_STEP","name":"closeBrowser","message":"Browser is closed","description":"","startTime":1531365437862,"endTime":1531365439354,"childRecords":[{"testStatus":{"stackTrace":"","statusValue":"PASSED"},"type":"MESSAGE","name":"","message":"Browser is closed","startTime":1531365439353,"endTime":0,"childRecords":[],"interuppted":false}],"interuppted":false},{"testStatus":{"stackTrace":"","statusValue":"PASSED"},"type":"MESSAGE","name":"","message":"Test Cases/TC01_LoginWithValidUsernamePassword","startTime":1531365439355,"endTime":0,"childRecords":[],"interuppted":false}],"interuppted":false},{"isOptional":false,"type":"TEST_CASE","name":"Test Cases/TC02_LoginWithInvalidUsernamePassword","id":"Test Cases/TC02_LoginWithInvalidUsernamePassword","source":"C:\\\\Users\\\\KHilmi\\\\Katalon Studio\\\\AMS_TestProject\\\\Test Cases\\\\TC02_LoginWithInvalidUsernamePassword.tc","message":"Test Cases/TC02_LoginWithInvalidUsernamePassword","description":"","startTime":1531365439365,"endTime":1531365446758,"childRecords":[{"testStatus":{"stackTrace":"","statusValue":"INFO"},"type":"MESSAGE","name":"","message":"Evaluating variables for test case","startTime":1531365439376,"endTime":0,"childRecords":[],"interuppted":false},{"index":1,"isIgnoredIfFailed":false,"type":"TEST_STEP","name":"openBrowser","message":"Browser is opened with url: \u0027\u0027","description":"","startTime":1531365439660,"endTime":1531365441983,"childRecords":[{"testStatus":{"stackTrace":"","statusValue":"PASSED"},"type":"MESSAGE","name":"","message":"Browser is opened with url: \u0027\u0027","startTime":1531365441983,"endTime":0,"childRecords":[],"interuppted":false}],"interuppted":false},{"index":2,"isIgnoredIfFailed":false,"type":"TEST_STEP","name":"navigateToUrl","message":"Navigate to \u0027http://localhost:57065/account/login\u0027 successfully","description":"","startTime":1531365441984,"endTime":1531365443458,"childRecords":[{"testStatus":{"stackTrace":"","statusValue":"PASSED"},"type":"MESSAGE","name":"","message":"Navigate to \u0027http://localhost:57065/account/login\u0027 successfully","startTime":1531365443457,"endTime":0,"childRecords":[],"interuppted":false}],"interuppted":false},{"index":3,"isIgnoredIfFailed":false,"type":"TEST_STEP","name":"setText","message":"Text \u0027Kamarul\u0027 is set on object \u0027Object Repository/TC01_OR/Page_Login/input_UserName\u0027","description":"","startTime":1531365443458,"endTime":1531365444032,"childRecords":[{"testStatus":{"stackTrace":"","statusValue":"PASSED"},"type":"MESSAGE","name":"","message":"Text \u0027Kamarul\u0027 is set on object \u0027Object Repository/TC01_OR/Page_Login/input_UserName\u0027","startTime":1531365444031,"endTime":0,"childRecords":[],"interuppted":false}],"interuppted":false},{"index":4,"isIgnoredIfFailed":false,"type":"TEST_STEP","name":"setText","message":"Text \u0027invalidpassword\u0027 is set on object \u0027Object Repository/TC01_OR/Page_Login/input_Password\u0027","description":"","startTime":1531365444032,"endTime":1531365444374,"childRecords":[{"testStatus":{"stackTrace":"","statusValue":"PASSED"},"type":"MESSAGE","name":"","message":"Text \u0027invalidpassword\u0027 is set on object \u0027Object Repository/TC01_OR/Page_Login/input_Password\u0027","startTime":1531365444373,"endTime":0,"childRecords":[],"interuppted":false}],"interuppted":false},{"index":5,"isIgnoredIfFailed":false,"type":"TEST_STEP","name":"click","message":"Object: \u0027Object Repository/TC01_OR/Page_Login/input_btn btn-primary\u0027 is clicked on","description":"","startTime":1531365444374,"endTime":1531365445377,"childRecords":[{"testStatus":{"stackTrace":"","statusValue":"PASSED"},"type":"MESSAGE","name":"","message":"Object: \u0027Object Repository/TC01_OR/Page_Login/input_btn btn-primary\u0027 is clicked on","startTime":1531365445376,"endTime":0,"childRecords":[],"interuppted":false}],"interuppted":false},{"index":6,"isIgnoredIfFailed":false,"type":"TEST_STEP","name":"verifyElementPresent","message":"Object \u0027Object Repository/TC02_OR/Page_Login/li_Invalid Login Attempt\u0027 is present","description":"","startTime":1531365445377,"endTime":1531365445552,"childRecords":[{"testStatus":{"stackTrace":"","statusValue":"WARNING"},"type":"MESSAGE","name":"","message":"Timeout \u00270\u0027 is invalid. Using default page load timeout: \u00275\u0027","startTime":1531365445381,"endTime":0,"childRecords":[],"interuppted":false},{"testStatus":{"stackTrace":"","statusValue":"PASSED"},"type":"MESSAGE","name":"","message":"Object \u0027Object Repository/TC02_OR/Page_Login/li_Invalid Login Attempt\u0027 is present","startTime":1531365445551,"endTime":0,"childRecords":[],"interuppted":false}],"interuppted":false},{"index":7,"isIgnoredIfFailed":false,"type":"TEST_STEP","name":"closeBrowser","message":"Browser is closed","description":"","startTime":1531365445552,"endTime":1531365446757,"childRecords":[{"testStatus":{"stackTrace":"","statusValue":"PASSED"},"type":"MESSAGE","name":"","message":"Browser is closed","startTime":1531365446757,"endTime":0,"childRecords":[],"interuppted":false}],"interuppted":false},{"testStatus":{"stackTrace":"","statusValue":"PASSED"},"type":"MESSAGE","name":"","message":"Test Cases/TC02_LoginWithInvalidUsernamePassword","startTime":1531365446757,"endTime":0,"childRecords":[],"interuppted":false}],"interuppted":false},{"isOptional":false,"type":"TEST_CASE","name":"Test Cases/TC03_LoginWithInvalidUsernameOnly","id":"Test Cases/TC03_LoginWithInvalidUsernameOnly","source":"C:\\\\Users\\\\KHilmi\\\\Katalon Studio\\\\AMS_TestProject\\\\Test Cases\\\\TC03_LoginWithInvalidUsernameOnly.tc","message":"Test Cases/TC03_LoginWithInvalidUsernameOnly","description":"","startTime":1531365446761,"endTime":1531365453389,"childRecords":[{"testStatus":{"stackTrace":"","statusValue":"INFO"},"type":"MESSAGE","name":"","message":"Evaluating variables for test case","startTime":1531365446769,"endTime":0,"childRecords":[],"interuppted":false},{"index":1,"isIgnoredIfFailed":false,"type":"TEST_STEP","name":"openBrowser","message":"Browser is opened with url: \u0027\u0027","description":"","startTime":1531365446958,"endTime":1531365449434,"childRecords":[{"testStatus":{"stackTrace":"","statusValue":"PASSED"},"type":"MESSAGE","name":"","message":"Browser is opened with url: \u0027\u0027","startTime":1531365449433,"endTime":0,"childRecords":[],"interuppted":false}],"interuppted":false},{"index":2,"isIgnoredIfFailed":false,"type":"TEST_STEP","name":"navigateToUrl","message":"Navigate to \u0027http://localhost:57065/account/login\u0027 successfully","description":"","startTime":1531365449434,"endTime":1531365450601,"childRecords":[{"testStatus":{"stackTrace":"","statusValue":"PASSED"},"type":"MESSAGE","name":"","message":"Navigate to \u0027http://localhost:57065/account/login\u0027 successfully","startTime":1531365450601,"endTime":0,"childRecords":[],"interuppted":false}],"interuppted":false},{"index":3,"isIgnoredIfFailed":false,"type":"TEST_STEP","name":"setText","message":"Text \u0027KHilmi\u0027 is set on object \u0027Object Repository/TC01_OR/Page_Login/input_UserName\u0027","description":"","startTime":1531365450602,"endTime":1531365451190,"childRecords":[{"testStatus":{"stackTrace":"","statusValue":"PASSED"},"type":"MESSAGE","name":"","message":"Text \u0027KHilmi\u0027 is set on object \u0027Object Repository/TC01_OR/Page_Login/input_UserName\u0027","startTime":1531365451189,"endTime":0,"childRecords":[],"interuppted":false}],"interuppted":false},{"index":4,"isIgnoredIfFailed":false,"type":"TEST_STEP","name":"setText","message":"Text \u0027Invalidpassword\u0027 is set on object \u0027Object Repository/TC01_OR/Page_Login/input_Password\u0027","description":"","startTime":1531365451190,"endTime":1531365451524,"childRecords":[{"testStatus":{"stackTrace":"","statusValue":"PASSED"},"type":"MESSAGE","name":"","message":"Text \u0027Invalidpassword\u0027 is set on object \u0027Object Repository/TC01_OR/Page_Login/input_Password\u0027","startTime":1531365451523,"endTime":0,"childRecords":[],"interuppted":false}],"interuppted":false},{"index":5,"isIgnoredIfFailed":false,"type":"TEST_STEP","name":"click","message":"Object: \u0027Object Repository/TC01_OR/Page_Login/input_btn btn-primary\u0027 is clicked on","description":"","startTime":1531365451524,"endTime":1531365452462,"childRecords":[{"testStatus":{"stackTrace":"","statusValue":"PASSED"},"type":"MESSAGE","name":"","message":"Object: \u0027Object Repository/TC01_OR/Page_Login/input_btn btn-primary\u0027 is clicked on","startTime":1531365452462,"endTime":0,"childRecords":[],"interuppted":false}],"interuppted":false},{"index":6,"isIgnoredIfFailed":false,"type":"TEST_STEP","name":"verifyElementPresent","message":"Object \u0027Object Repository/TC02_OR/Page_Login/li_Invalid Login Attempt\u0027 is present","description":"","startTime":1531365452463,"endTime":1531365452563,"childRecords":[{"testStatus":{"stackTrace":"","statusValue":"WARNING"},"type":"MESSAGE","name":"","message":"Timeout \u00270\u0027 is invalid. Using default page load timeout: \u00275\u0027","startTime":1531365452469,"endTime":0,"childRecords":[],"interuppted":false},{"testStatus":{"stackTrace":"","statusValue":"PASSED"},"type":"MESSAGE","name":"","message":"Object \u0027Object Repository/TC02_OR/Page_Login/li_Invalid Login Attempt\u0027 is present","startTime":1531365452563,"endTime":0,"childRecords":[],"interuppted":false}],"interuppted":false},{"index":7,"isIgnoredIfFailed":false,"type":"TEST_STEP","name":"closeBrowser","message":"Browser is closed","description":"","startTime":1531365452564,"endTime":1531365453388,"childRecords":[{"testStatus":{"stackTrace":"","statusValue":"PASSED"},"type":"MESSAGE","name":"","message":"Browser is closed","startTime":1531365453387,"endTime":0,"childRecords":[],"interuppted":false}],"interuppted":false},{"testStatus":{"stackTrace":"","statusValue":"PASSED"},"type":"MESSAGE","name":"","message":"Test Cases/TC03_LoginWithInvalidUsernameOnly","startTime":1531365453388,"endTime":0,"childRecords":[],"interuppted":false}],"interuppted":false},{"isOptional":false,"type":"TEST_CASE","name":"Test Cases/TC04_LoginWithInvalidPasswordOnly","id":"Test Cases/TC04_LoginWithInvalidPasswordOnly","source":"C:\\\\Users\\\\KHilmi\\\\Katalon Studio\\\\AMS_TestProject\\\\Test Cases\\\\TC04_LoginWithInvalidPasswordOnly.tc","message":"Test Cases/TC04_LoginWithInvalidPasswordOnly","description":"","startTime":1531365453393,"endTime":1531365460809,"childRecords":[{"testStatus":{"stackTrace":"","statusValue":"INFO"},"type":"MESSAGE","name":"","message":"Evaluating variables for test case","startTime":1531365453410,"endTime":0,"childRecords":[],"interuppted":false},{"index":1,"isIgnoredIfFailed":false,"type":"TEST_STEP","name":"openBrowser","message":"Browser is opened with url: \u0027\u0027","description":"","startTime":1531365453644,"endTime":1531365456012,"childRecords":[{"testStatus":{"stackTrace":"","statusValue":"PASSED"},"type":"MESSAGE","name":"","message":"Browser is opened with url: \u0027\u0027","startTime":1531365456012,"endTime":0,"childRecords":[],"interuppted":false}],"interuppted":false},{"index":2,"isIgnoredIfFailed":false,"type":"TEST_STEP","name":"navigateToUrl","message":"Navigate to \u0027http://localhost:57065/account/login\u0027 successfully","description":"","startTime":1531365456012,"endTime":1531365457848,"childRecords":[{"testStatus":{"stackTrace":"","statusValue":"PASSED"},"type":"MESSAGE","name":"","message":"Navigate to \u0027http://localhost:57065/account/login\u0027 successfully","startTime":1531365457847,"endTime":0,"childRecords":[],"interuppted":false}],"interuppted":false},{"index":3,"isIgnoredIfFailed":false,"type":"TEST_STEP","name":"setText","message":"Text \u0027Kamarul\u0027 is set on object \u0027Object Repository/TC01_OR/Page_Login/input_UserName\u0027","description":"","startTime":1531365457848,"endTime":1531365458317,"childRecords":[{"testStatus":{"stackTrace":"","statusValue":"PASSED"},"type":"MESSAGE","name":"","message":"Text \u0027Kamarul\u0027 is set on object \u0027Object Repository/TC01_OR/Page_Login/input_UserName\u0027","startTime":1531365458316,"endTime":0,"childRecords":[],"interuppted":false}],"interuppted":false},{"index":4,"isIgnoredIfFailed":false,"type":"TEST_STEP","name":"setText","message":"Text \u0027P@ssw0rd\u0027 is set on object \u0027Object Repository/TC01_OR/Page_Login/input_Password\u0027","description":"","startTime":1531365458317,"endTime":1531365458601,"childRecords":[{"testStatus":{"stackTrace":"","statusValue":"PASSED"},"type":"MESSAGE","name":"","message":"Text \u0027P@ssw0rd\u0027 is set on object \u0027Object Repository/TC01_OR/Page_Login/input_Password\u0027","startTime":1531365458600,"endTime":0,"childRecords":[],"interuppted":false}],"interuppted":false},{"index":5,"isIgnoredIfFailed":false,"type":"TEST_STEP","name":"click","message":"Object: \u0027Object Repository/TC01_OR/Page_Login/input_btn btn-primary\u0027 is clicked on","description":"","startTime":1531365458602,"endTime":1531365459868,"childRecords":[{"testStatus":{"stackTrace":"","statusValue":"PASSED"},"type":"MESSAGE","name":"","message":"Object: \u0027Object Repository/TC01_OR/Page_Login/input_btn btn-primary\u0027 is clicked on","startTime":1531365459867,"endTime":0,"childRecords":[],"interuppted":false}],"interuppted":false},{"index":6,"isIgnoredIfFailed":false,"type":"TEST_STEP","name":"verifyElementPresent","message":"Object \u0027Object Repository/TC02_OR/Page_Login/li_Invalid Login Attempt\u0027 is present","description":"","startTime":1531365459868,"endTime":1531365459966,"childRecords":[{"testStatus":{"stackTrace":"","statusValue":"WARNING"},"type":"MESSAGE","name":"","message":"Timeout \u00270\u0027 is invalid. Using default page load timeout: \u00275\u0027","startTime":1531365459876,"endTime":0,"childRecords":[],"interuppted":false},{"testStatus":{"stackTrace":"","statusValue":"PASSED"},"type":"MESSAGE","name":"","message":"Object \u0027Object Repository/TC02_OR/Page_Login/li_Invalid Login Attempt\u0027 is present","startTime":1531365459965,"endTime":0,"childRecords":[],"interuppted":false}],"interuppted":false},{"index":7,"isIgnoredIfFailed":false,"type":"TEST_STEP","name":"closeBrowser","message":"Browser is closed","description":"","startTime":1531365459966,"endTime":1531365460805,"childRecords":[{"testStatus":{"stackTrace":"","statusValue":"PASSED"},"type":"MESSAGE","name":"","message":"Browser is closed","startTime":1531365460804,"endTime":0,"childRecords":[],"interuppted":false}],"interuppted":false},{"testStatus":{"stackTrace":"","statusValue":"PASSED"},"type":"MESSAGE","name":"","message":"Test Cases/TC04_LoginWithInvalidPasswordOnly","startTime":1531365460807,"endTime":0,"childRecords":[],"interuppted":false}],"interuppted":false},{"isOptional":false,"type":"TEST_CASE","name":"Test Cases/TC05_LoginWithValidUsernamePasswordButFail","id":"Test Cases/TC05_LoginWithValidUsernamePasswordButFail","source":"C:\\\\Users\\\\KHilmi\\\\Katalon Studio\\\\AMS_TestProject\\\\Test Cases\\\\TC05_LoginWithValidUsernamePasswordButFail.tc","message":"Test Cases/TC05_LoginWithValidUsernamePasswordButFail FAILED because (of) Unable to verify object is present (Root cause: java.lang.IllegalArgumentException: Object is null)","description":"","startTime":1531365460815,"endTime":1531365471143,"childRecords":[{"testStatus":{"stackTrace":"","statusValue":"INFO"},"type":"MESSAGE","name":"","message":"Evaluating variables for test case","startTime":1531365460826,"endTime":0,"childRecords":[],"interuppted":false},{"index":1,"isIgnoredIfFailed":false,"type":"TEST_STEP","name":"openBrowser","message":"Browser is opened with url: \u0027\u0027","description":"","startTime":1531365461106,"endTime":1531365463397,"childRecords":[{"testStatus":{"stackTrace":"","statusValue":"PASSED"},"type":"MESSAGE","name":"","message":"Browser is opened with url: \u0027\u0027","startTime":1531365463396,"endTime":0,"childRecords":[],"interuppted":false}],"interuppted":false},{"index":2,"isIgnoredIfFailed":false,"type":"TEST_STEP","name":"navigateToUrl","message":"Navigate to \u0027http://localhost:57065/account/login\u0027 successfully","description":"","startTime":1531365463397,"endTime":1531365464571,"childRecords":[{"testStatus":{"stackTrace":"","statusValue":"PASSED"},"type":"MESSAGE","name":"","message":"Navigate to \u0027http://localhost:57065/account/login\u0027 successfully","startTime":1531365464570,"endTime":0,"childRecords":[],"interuppted":false}],"interuppted":false},{"index":3,"isIgnoredIfFailed":false,"type":"TEST_STEP","name":"setText","message":"Text \u0027KHilmi\u0027 is set on object \u0027Object Repository/TC01_OR/Page_Login/input_UserName\u0027","description":"","startTime":1531365464571,"endTime":1531365465160,"childRecords":[{"testStatus":{"stackTrace":"","statusValue":"PASSED"},"type":"MESSAGE","name":"","message":"Text \u0027KHilmi\u0027 is set on object \u0027Object Repository/TC01_OR/Page_Login/input_UserName\u0027","startTime":1531365465159,"endTime":0,"childRecords":[],"interuppted":false}],"interuppted":false},{"index":4,"isIgnoredIfFailed":false,"type":"TEST_STEP","name":"setText","message":"Text \u0027P@ssw0rd\u0027 is set on object \u0027Object Repository/TC01_OR/Page_Login/input_Password\u0027","description":"","startTime":1531365465160,"endTime":1531365465413,"childRecords":[{"testStatus":{"stackTrace":"","statusValue":"PASSED"},"type":"MESSAGE","name":"","message":"Text \u0027P@ssw0rd\u0027 is set on object \u0027Object Repository/TC01_OR/Page_Login/input_Password\u0027","startTime":1531365465412,"endTime":0,"childRecords":[],"interuppted":false}],"interuppted":false},{"index":5,"isIgnoredIfFailed":false,"type":"TEST_STEP","name":"click","message":"Object: \u0027Object Repository/TC01_OR/Page_Login/input_btn btn-primary\u0027 is clicked on","description":"","startTime":1531365465413,"endTime":1531365469177,"childRecords":[{"testStatus":{"stackTrace":"","statusValue":"PASSED"},"type":"MESSAGE","name":"","message":"Object: \u0027Object Repository/TC01_OR/Page_Login/input_btn btn-primary\u0027 is clicked on","startTime":1531365469176,"endTime":0,"childRecords":[],"interuppted":false}],"interuppted":false},{"index":6,"isIgnoredIfFailed":false,"type":"TEST_STEP","name":"click","message":"Object: \u0027Object Repository/TC01_OR/Page_Asset Management System/h2_Dashboard\u0027 is clicked on","description":"","startTime":1531365469177,"endTime":1531365469696,"childRecords":[{"testStatus":{"stackTrace":"","statusValue":"PASSED"},"type":"MESSAGE","name":"","message":"Object: \u0027Object Repository/TC01_OR/Page_Asset Management System/h2_Dashboard\u0027 is clicked on","startTime":1531365469695,"endTime":0,"childRecords":[],"interuppted":false}],"interuppted":false},{"attachment":"1531365469712.png","index":7,"isIgnoredIfFailed":false,"type":"TEST_STEP","name":"verifyElementPresent","message":"Unable to verify object is present (Root cause: java.lang.IllegalArgumentException: Object is null)","description":"","startTime":1531365469696,"endTime":1531365470174,"childRecords":[{"testStatus":{"stackTrace":"","statusValue":"WARNING"},"type":"MESSAGE","name":"","message":"Test object with id \u0027Object Repository/TC01_OR/Page_Asset Management System/h2_MainDashboard\u0027 does not exist","startTime":1531365469697,"endTime":0,"childRecords":[],"interuppted":false},{"testStatus":{"stackTrace":"","statusValue":"WARNING"},"type":"MESSAGE","name":"","message":"Test object with id \u0027Object Repository/\u0027 does not exist","startTime":1531365469708,"endTime":0,"childRecords":[],"interuppted":false},{"testStatus":{"stackTrace":"","statusValue":"FAILED"},"attachment":"1531365469712.png","type":"MESSAGE","name":"","message":"Unable to verify object is present (Root cause: java.lang.IllegalArgumentException: Object is null)","startTime":1531365470173,"endTime":0,"childRecords":[],"interuppted":false}],"interuppted":false},{"index":8,"isIgnoredIfFailed":false,"type":"TEST_STEP","name":"closeBrowser","message":"Browser is closed","description":"","startTime":1531365470174,"endTime":1531365471141,"childRecords":[{"testStatus":{"stackTrace":"","statusValue":"PASSED"},"type":"MESSAGE","name":"","message":"Browser is closed","startTime":1531365471141,"endTime":0,"childRecords":[],"interuppted":false}],"interuppted":false},{"testStatus":{"stackTrace":"","statusValue":"FAILED"},"type":"MESSAGE","name":"","message":"Test Cases/TC05_LoginWithValidUsernamePasswordButFail FAILED because (of) Unable to verify object is present (Root cause: java.lang.IllegalArgumentException: Object is null)","startTime":1531365471141,"endTime":0,"childRecords":[],"interuppted":false}],"interuppted":false}],"interuppted":false}